papertrack/__init__.py
papertrack/__main__.py
papertrack/curses.py
papertrack/core/Component.py
papertrack/core/Configuration.py
papertrack/core/Database.py
papertrack/core/Loggable.py
papertrack/core/__init__.py
papertrack/simple/__init__.py
test/TestConfiguration.py
test/__init__.py
test/__main__.py
papertrack-0.2.dist-info/LICENSE
papertrack-0.2.dist-info/METADATA
papertrack-0.2.dist-info/WHEEL
papertrack-0.2.dist-info/entry_points.txt
papertrack-0.2.dist-info/top_level.txt
papertrack-0.2.dist-info/RECORD
