Metadata-Version: 2.1
Name: papertrack
Version: 0.2
Summary: Tool and library for tracking document metadata and automatic download and structuring of documents
Home-page: https://github.com/fantastic001/papertrack
Author: Stefan Nožinić
Author-email: stefan@lugons.org
License: UNKNOWN
Project-URL: Bug Tracker, https://github.com/fantastic001/papertrack/issues
Platform: UNKNOWN
Classifier: Programming Language :: Python :: 3
Classifier: License :: OSI Approved :: MIT License
Classifier: Operating System :: OS Independent
Requires-Python: >=3.6
License-File: LICENSE
